{"children": [{"children": [{"type": "run routine", "name": "Convert protocols", "option": "ORCM PROTOCOLS", "ien": "8510"}, {"type": "run routine", "name": "Enter/edit actions", "option": "ORCM ACTIONS", "ien": "8516"}, {"type": "run routine", "name": "List Primary Order Menus", "option": "ORCM LIST ORDER MENUS", "ien": "8674"}, {"type": "run routine", "name": "Disable/Enable order dialogs", "option": "ORCM DISABLE", "ien": "8692"}, {"type": "run routine", "name": "Quick Order Mixed-Case Report", "option": "OR QO CASE REPORT", "ien": "11496"}, {"type": "run routine", "name": "Enter/edit quick orders", "option": "ORCM QUICK ORDERS", "ien": "8511"}, {"type": "run routine", "name": "Enter/edit prompts", "option": "ORCM PROMPTS", "ien": "8512"}, {"type": "run routine", "name": "Enter/edit order sets", "option": "ORCM ORDER SETS", "ien": "8514"}, {"type": "action", "name": "Convert IV Inpatient QO to Infusion QO", "option": "OR CONVERT INP TO IV", "ien": "10931"}, {"type": "run routine", "name": "Enter/edit order menus", "option": "ORCM MENU", "ien": "8509"}, {"type": "action", "name": "IV Additive Frequency Utility", "option": "OR IV ADD FREQ UTILITY", "ien": "11227"}, {"type": "action", "name": "Assign Primary Order Menu", "option": "OR PARAM ADD MENU", "ien": "8618"}, {"children": [{"type": "run routine", "name": "Edit VBECS item display names", "option": "ORCM VBECS OI EDIT", "ien": "10975"}, {"type": "run routine", "name": "Enter/edit orderable items", "option": "ORCM ORDERABLES", "ien": "8508"}, {"type": "run routine", "name": "Enter/edit QO restriction", "option": "ORCM QO ITEMS", "ien": "9581"}, {"type": "run routine", "name": "Search/replace orderables", "option": "ORCM SEARCH/REPLACE ORDERABLES", "ien": "9582"}], "type": "menu", "name": "Manage orderable items", "option": "ORCM ORDERABLES MENU", "ien": "9583"}, {"type": "run routine", "name": "Edit personal quick orders by user", "option": "ORCM QUICK ORDERS BY USER", "ien": "10690"}, {"type": "run routine", "name": "Quick Order Free-Text Report", "option": "OR QO FREETEXT REPORT", "ien": "11497"}, {"type": "run routine", "name": "Search/replace components", "option": "ORCM SEARCH/REPLACE", "ien": "8517"}, {"type": "run routine", "name": "Review Quick Orders for Inactive ICD9 Codes", "option": "ORCM GMRC CSV CHECK", "ien": "9766"}, {"type": "run routine", "name": "Enter/edit generic orders", "option": "ORCM ORDERS", "ien": "8513"}, {"type": "action", "name": "Medication Quick Order Report", "option": "OR MEDICATION QO CHECKER", "ien": "10891"}], "type": "menu", "name": "Order Menu Management", "option": "ORCM MGMT", "ien": "8515"}, {"type": "run routine", "name": "Review protocol file", "option": "ORCM REVIEW PROTOCOLS", "ien": "8518"}, {"type": "run routine", "name": "Locate protocols", "option": "ORCM FIND PROTOCOL", "ien": "8521"}, {"type": "run routine", "name": "Estimate global growth for CPRS", "option": "ORCM ESTIMATE", "ien": "8522"}], "type": "menu", "name": "Protocol Conversion Utilities", "option": "ORCM CONVERSION UTILITIES", "ien": "8520"}