{"name": "Conversion Menu", "lock": "XUPROG", "ien": "11038", "type": "menu", "children": [{"type": "run routine", "name": "Convert OUTPATIENT CLINIC RECALL PARAM", "option": "SDRR CONVERSION PARAMS FILE", "ien": "11039"}, {"type": "run routine", "name": "Convert OUTPATIENT CLINIC RECALL TEAM", "option": "SDRR CONVERSION TEAM FILE", "ien": "11040"}, {"type": "run routine", "name": "Convert OUTPATIENT CLINIC RECALL", "option": "SDRR CONV OUTPATIENT RECALL", "ien": "11043"}, {"type": "run routine", "name": "Convert OUTPATIENT CLINIC RECALL PROVIDERS", "option": "SDRR CONVERSION PROVIDER FILE", "ien": "11042"}, {"type": "run routine", "name": "Convert OUTPATIENT CLINIC RECALL APPT TYPES", "option": "SDRR CON RECALL APPT TYPES", "ien": "11041"}], "option": "SDRR IRM MENU"}