{"children": [{"name": "Enter/Edit Document", "option": "TIU ENTER/EDIT TRANSCRIBER", "ien": "7787"}, {"name": "Review/Edit Documents", "option": "TIU BROWSE DOC TRANSCRIPTION", "ien": "10016"}, {"name": "List Documents for Transcription", "option": "TIU REVIEW UNTRANSCRIBED DOCS", "ien": "10015"}, {"name": "Enter/Edit Discharge Summary", "option": "TIU ENTER/EDIT DS", "ien": "7772"}, {"children": [{"name": "Upload Documents", "option": "TIU UPLOAD DOCUMENTS", "ien": "7760"}, {"name": "Help for Upload Utility", "option": "TIU UPLOAD HELP", "ien": "7761"}], "name": "Upload Menu", "option": "TIU UPLOAD MENU", "ien": "7762"}], "name": "Text Integration Utilities (Transcriptionist)", "option": "TIU MAIN MENU TRANSCRIPTION", "ien": "7740"}