{"children": [{"children": [{"name": "Edit Clinic Med Orders Start Date/Time", "option": "PSJ ECO", "ien": "11469"}, {"name": "Discontinue All of a Patient's Orders", "option": "PSJU CA", "ien": "3623"}, {"lock": "PSJU PL", "name": "Edit Patient's Default Stop Date", "option": "PSJU CPDD", "ien": "3647"}, {"name": "Order Entry", "option": "PSJU NE", "ien": "3605"}, {"name": "Align Labels (Unit Dose)", "option": "PSJU AL", "ien": "3719"}, {"name": "Non-Verified/Pending Orders", "option": "PSJU VBW", "ien": "3622"}, {"name": "Check Drug Interaction", "option": "PSJ CHECK DRUG INTERACTION", "ien": "11445"}, {"name": "Edit Inpatient User Parameters", "option": "PSJ UEUP", "ien": "3709"}, {"name": "Inpatient Profile", "option": "PSJ PR", "ien": "3701"}, {"children": [{"name": "Dispense Drug Look-Up", "option": "PSJU INQ DRUG", "ien": "3626"}, {"name": "Standard Schedules", "option": "PSJU INQ STD SCHD", "ien": "3607"}], "name": "INQuiries Menu", "option": "PSJU INQMGR", "ien": "3629"}, {"lock": "PSJU MGR", "children": [{"name": "Ward Groups", "option": "PSJU EWG", "ien": "3618"}, {"name": "Non-Standard Schedule Report", "option": "PSJU NSS REPORT", "ien": "10069"}, {"name": "Order Set Enter/Edit", "option": "PSJU OSE", "ien": "3643"}, {"name": "PATient Order Purge", "option": "PSJU PO PURGE", "ien": "3639"}, {"children": [{"name": "AUto-Discontinue Set-Up", "option": "PSJ AC SET-UP", "ien": "3713"}, {"name": "Inpatient Ward Parameters Edit", "option": "PSJ IWP EDIT", "ien": "3711"}, {"name": "Systems Parameters Edit", "option": "PSJ SYS EDIT", "ien": "3718"}, {"name": "Clinic Definition", "option": "PSJ CD", "ien": "10371"}, {"name": "Inpatient User Parameters Edit", "option": "PSJ SEUP", "ien": "3710"}], "name": "PARameters Edit Menu", "option": "PSJ PARAM EDIT MENU", "ien": "3721"}, {"children": [{"name": "PUrge Pick Lists", "option": "PSJU PLPRG", "ien": "3633"}, {"name": "Delete a Pick List", "option": "PSJU PLDEL", "ien": "3641"}, {"name": "PIck List Auto Purge Set/Reset", "option": "PSJU PLAPS", "ien": "3632"}], "name": "PIck List Menu", "option": "PSJU PL MENU", "ien": "3722"}, {"name": "Clinic Groups", "option": "PSJU ECG", "ien": "10244"}, {"children": [{"name": "AMIS (Cost per Ward)", "option": "PSJU AMIS", "ien": "3631"}, {"name": "Patients on Specific Drug(s)", "option": "PSJ PDV", "ien": "3727"}, {"name": "Service (Total Cost per)", "option": "PSJU SCT", "ien": "3634"}, {"name": "Drug (Cost and/or Amount)", "option": "PSJU DCT", "ien": "3635"}, {"name": "PRovider (Cost per)", "option": "PSJU PRVR", "ien": "3638"}, {"name": "Total Cost to Date  (Current Patients)", "option": "PSJU TCTD", "ien": "3636"}], "name": "MANagement Reports Menu", "option": "PSJU MNGMT REPORTS", "ien": "3637"}, {"name": "Non-Standard Schedule Search", "option": "PSJU NSS SEARCH", "ien": "10068"}, {"name": "Administering Teams", "option": "PSJU AT", "ien": "3611"}], "name": "Supervisor's Menu", "option": "PSJU FILE", "ien": "3615"}, {"name": "Hold All of a Patient's Orders", "option": "PSJU HOLD ALL", "ien": "3645"}, {"name": "Label Print/Reprint", "option": "PSJU LABEL", "ien": "3621"}, {"lock": "PSJU PL", "children": [{"lock": "PSJU PL", "name": "EXtra Units Dispensed", "option": "PSJU EUD", "ien": "3627"}, {"lock": "PSJU PL", "name": "Update Pick List", "option": "PSJU PLUP", "ien": "3614"}, {"lock": "PSJU PL", "name": "ENter Units Dispensed", "option": "PSJU PLDP", "ien": "3612"}, {"lock": "PSJU PL", "name": "Send Pick List to ATC", "option": "PSJU PLATCS", "ien": "3648"}, {"lock": "PSJU PL", "name": "Pick List", "option": "PSJU PL", "ien": "3609"}, {"lock": "PSJU PL", "name": "Report Returns", "option": "PSJU RET", "ien": "3608"}, {"lock": "PSJU PL", "name": "Reprint Pick List", "option": "PSJU PLRP", "ien": "3624"}], "name": "PIck List Menu", "option": "PSJU PLMGR", "ien": "3610"}, {"children": [{"name": "INpatient Stop Order Notices", "option": "PSJ EXP", "ien": "3613"}, {"name": "7 Day MAR", "option": "PSJU 7D MAR", "ien": "3649"}, {"name": "AUthorized Absence/Discharge Summary", "option": "PSJU DS", "ien": "3651"}, {"name": "Action Profile #2", "option": "PSJU AP-2", "ien": "3652"}, {"name": "Patient Profile (Extended)", "option": "PSJ EXTP", "ien": "3724"}, {"name": "Medications Due Worksheet", "option": "PSJ MDWS", "ien": "3725"}, {"name": "Action Profile #1", "option": "PSJU AP-1", "ien": "3644"}, {"name": "Free Text Dosage Report", "option": "PSJU DOSAGE REPORT", "ien": "9369"}, {"name": "14 Day MAR", "option": "PSJU 14D MAR", "ien": "3650"}, {"name": "24 Hour MAR", "option": "PSJU 24H MAR", "ien": "3619"}, {"name": "Extra Units Dispensed Report", "option": "PSJU EUDD", "ien": "3726"}], "name": "Reports Menu", "option": "PSJU REPORTS", "ien": "3630"}, {"name": "Inpatient Order Entry", "option": "PSJ OE", "ien": "3702"}, {"name": "PAtient Profile (Unit Dose)", "option": "PSJU PR", "ien": "3606"}], "name": "Unit Dose Medications", "option": "PSJU MGR", "ien": "3604"}, {"children": [{"name": "Edit Clinic Med Orders Start Date/Time", "option": "PSJ ECO", "ien": "11469"}], "name": "Clinic Orders Menu", "option": "PSJ CLINIC ORDERS MENU", "ien": "11468"}, {"children": [{"name": "Ward List (IV)", "option": "PSJI WARD", "ien": "3670"}, {"lock": "PSJI MGR", "children": [{"name": "COmpile IV Statistics (IV)", "option": "PSJI COMPILE STATS", "ien": "3687"}, {"name": "Recompile Stats File (IV)", "option": "PSJI RECOMPILE", "ien": "3696"}, {"children": [{"name": "AMIS (IV)", "option": "PSJI AMIS", "ien": "3689"}, {"name": "Patient Cost Report (132 COLUMNS) (IV)", "option": "PSJI PATIENT COST", "ien": "3692"}, {"name": "ACtive Order Report by Ward/Drug (IV)", "option": "PSJI AOR", "ien": "3698"}, {"name": "Ward/Drug Usage Report (132 COLUMNS) (IV)", "option": "PSJI WARD/DRUG USAGE REPORT", "ien": "3693"}, {"name": "Patients on Specific Drug(s)", "option": "PSJ PDV", "ien": "3727"}, {"name": "Drug Cost Report (132 COLUMNS) (IV)", "option": "PSJI DRUG COST REPORT", "ien": "3691"}, {"name": "PRovider Drug Cost Report (132 COLUMNS) (IV)", "option": "PSJI PROVIDER REPORT", "ien": "3690"}], "name": "Management Reports (IV)", "option": "PSJI MANAGEMENT REPORTS", "ien": "3694"}, {"name": "CAtegory File (IV)", "option": "PSJI IVCATEGORY", "ien": "8152"}, {"name": "SIte Parameters (IV)", "option": "PSJI SITE PARAMETERS", "ien": "3659"}, {"lock": "PSJI PURGE", "children": [{"name": "Delete Orders (IV)", "option": "PSJI DELETE ORDER", "ien": "3681"}, {"name": "Purge Expired Orders (IV)", "option": "PSJI PURGE ORDERS", "ien": "3657"}], "name": "PUrge Data (IV)", "option": "PSJI PURGE", "ien": "3679"}, {"name": "AUto-Discontinue Set-Up", "option": "PSJ AC SET-UP", "ien": "3713"}], "name": "SUPervisor's Menu (IV)", "option": "PSJI SUPERVISOR", "ien": "3675"}, {"name": "Order Entry (IV)", "option": "PSJI ORDER", "ien": "3714"}, {"children": [{"name": "Align Labels (IV)", "option": "PSJI ALIGNMENT", "ien": "3653"}, {"name": "Reprint Scheduled Labels (IV)", "option": "PSJI LBLR", "ien": "3705"}, {"name": "Test Control Codes (IV)", "option": "PSJI CONTROL CODES", "ien": "9466"}, {"name": "Scheduled Labels (IV)", "option": "PSJI LBLS", "ien": "3662"}, {"name": "Individual Labels (IV)", "option": "PSJI LBLI", "ien": "3661"}], "name": "Label Menu (IV)", "option": "PSJI LBLMENU", "ien": "3674"}, {"name": "Check Drug Interaction", "option": "PSJ CHECK DRUG INTERACTION", "ien": "11445"}, {"children": [{"name": "Reprint Labels from Suspense (IV)", "option": "PSJI SUSREP", "ien": "3685"}, {"name": "Manufacturing Record for Suspense (IV)", "option": "PSJI SUSMAN", "ien": "3669"}, {"name": "Delete Labels from Suspense (IV)", "option": "PSJI SUSLBDEL", "ien": "3688"}, {"name": "Labels from Suspense (IV)", "option": "PSJI SUSLBLS", "ien": "3667"}, {"name": "Suspense List (IV)", "option": "PSJI SUSLIST", "ien": "3668"}, {"name": "Individual Order Suspension (IV)", "option": "PSJI INDIVIDUAL SUSPENSE", "ien": "3655"}], "name": "SUSpense Functions (IV)", "option": "PSJI SUSMENU", "ien": "3672"}, {"name": "Profile (IV)", "option": "PSJI PROFILE", "ien": "3664"}, {"name": "Update Daily Ward List (IV)", "option": "PSJI UP", "ien": "3671"}, {"name": "Inpatient Order Entry", "option": "PSJ OE", "ien": "3702"}, {"name": "Barcode ID - Return and Destroy (IV)", "option": "PSJI RETURN BY BARCODE ID", "ien": "9580"}, {"name": "Inpatient Profile", "option": "PSJ PR", "ien": "3701"}, {"name": "Manufacturing List (IV)", "option": "PSJI MAN", "ien": "3663"}, {"name": "Drug Inquiry (IV)", "option": "PSJI DRUG INQUIRY", "ien": "3678"}, {"name": "Edit Clinic Med Orders Start Date/Time", "option": "PSJ ECO", "ien": "11469"}, {"name": "Change to Another IV Room (IV)", "option": "PSJI CHANGE", "ien": "3700"}, {"name": "RETurns and Destroyed Entry (IV)", "option": "PSJI RETURNS", "ien": "3658"}, {"name": "Change Report/Label Devices (IV)", "option": "PSJI DEVICE", "ien": "3654"}, {"children": [{"name": "INpatient Stop Order Notices", "option": "PSJ EXP", "ien": "3613"}, {"name": "Active Order List (IV)", "option": "PSJI ACTIVE", "ien": "3656"}, {"name": "IV Drug Formulary Report (IV)", "option": "PSJI DRUG FORM", "ien": "3686"}, {"name": "Patient Profile Report (IV)", "option": "PSJI PROFILE REPORT", "ien": "3677"}, {"name": "Renewal List (IV)", "option": "PSJI RNL", "ien": "3665"}], "name": "REPorts (IV)", "option": "PSJI REPORTS", "ien": "3676"}], "name": "IV Menu", "option": "PSJI MGR", "ien": "3673"}], "name": "PHARMACY MASTER MENU", "option": "PHARMACY MASTER MENU", "ien": "11467"}