{"children": [{"type": "run routine", "name": "Component Install History", "option": "VFD IT FIND INSTALL HISTORY", "ien": "11959"}, {"type": "run routine", "name": "Update 1st and 2nd Lines and Dates", "option": "VFD IT ROUTINE UPDATE", "ien": "10949"}, {"type": "run routine", "name": "Delete Routines (VFD)", "option": "VFD IT DELETE ROUTINE(S)", "ien": "11133"}, {"type": "run routine", "name": "Pointer Report", "option": "VFD IT POINTER REPORT", "ien": "11961"}, {"type": "run routine", "name": "VFD Start one RPC Broker Listener", "option": "VFD XWB START LISTENER", "ien": "10955"}, {"type": "run routine", "name": "Save/Restore Routines", "option": "VFD IT SAVE/RESTORE ROUTINES", "ien": "10951"}, {"type": "run routine", "name": "Routine Size Report", "option": "VFD IT ROUTINE SIZE", "ien": "10950"}, {"type": "run routine", "name": "VFD Stop one RPC Broker Listener", "option": "VFD XWB STOP LISTENER", "ien": "10966"}, {"type": "run routine", "name": "Routine Checksum Report", "option": "VFD IT CHECKSUM REPORT", "ien": "11962"}, {"type": "run routine", "name": "DD Namespace/Numberspace Report", "option": "VFD IT DD NAME NUMBERSPACE", "ien": "11960"}], "type": "menu", "name": "Developer Tools", "option": "VFD IT TOOLS", "ien": "10948"}