{"children": [{"type": "action", "name": "Label Reprint for CS RXs Report", "option": "PSD NM RX REPRINT", "ien": "9652"}, {"type": "action", "name": "CS Balance Adjustments Report", "option": "PSD NM CS ADJ", "ien": "9654"}, {"type": "run routine", "name": "Option Access By User", "option": "pims", "ien": "67"}, {"type": "action", "name": "Patients Without VA Visit Report", "option": "PSD NM RX WITHOUT VA", "ien": "9656"}, {"type": "action", "name": "CS RXs by Same Person Report", "option": "PSD NM RX SAME PERSON", "ien": "9655"}, {"type": "action", "name": "CS Application Security Key Report", "option": "PSD NM SECURITY KEY", "ien": "9657"}, {"type": "action", "name": "Partial Request for CS RXs Report", "option": "PSD NM RX PARTIAL", "ien": "9653"}], "type": "menu", "name": "CS Monitoring Menu", "option": "PSD NM MENU", "ien": "9651"}